pe_carve/__init__.py
pe_carve/pe_carve.py
pe_carver-2.0.0.dist-info/LICENSE
pe_carver-2.0.0.dist-info/METADATA
pe_carver-2.0.0.dist-info/WHEEL
pe_carver-2.0.0.dist-info/entry_points.txt
pe_carver-2.0.0.dist-info/top_level.txt
pe_carver-2.0.0.dist-info/RECORD
