Metadata-Version: 2.1
Name: pe-carver
Version: 2.0.0
Summary: Basic PE file carver for Python 3
Author: Brian Baskin (@bbaskin)
Author-email: "Corey Forman (digitalsleuth)" <github@digitalsleuth.ca>
Maintainer-email: "Corey Forman (digitalsleuth)" <github@digitalsleuth.ca>
License: Apache License
Project-URL: Homepage, https://github.com/digitalsleuth/pe-carver
Keywords: digital forensics,dfir,pe-carver,pe_carve
Classifier: Development Status :: 5 - Production/Stable
Classifier: Programming Language :: Python :: 3
Classifier: License :: OSI Approved :: Apache Software License
Classifier: Operating System :: OS Independent
Requires-Python: >=3.6
License-File: LICENSE
Requires-Dist: bitstring
Requires-Dist: pefile
